{"is_source_file": false, "format": "", "description": "", "external_files": [], "external_methods": [], "published": [], "classes": [], "methods": [], "calls": [], "search-terms": [], "state": 2, "file_id": 2, "knowledge_revision": 114, "git_revision": "790aaabd9d99dda104dd56017b48dd9769093534", "revision_history": [{"67": "c435314a6e807ec09f8a7ce87b95dcfdd46d4a72"}, {"114": "790aaabd9d99dda104dd56017b48dd9769093534"}], "hash": "ac2785b9999598b775f7a95e71aaf6b5", "format-version": 4, "code-base-name": "weekly_report_frontend", "filename": "weekly_report_frontend/README.md"}